[{"id":1,"name":"James Webb","year":"2022","country":"EUA","destination":"Espaço Interestelar"},{"id":2,"name":"Myke Jokes","year":"2022","country":"URSS","destination":"Espaço Interestelar"},{"id":3,"name":"Martha Wilk","year":"2023","country":"Japão","destination":"Marte"},{"id":1687404225945,"name":"Dignus Est","year":"2029","country":"Croácia","destination":"Pluto"},{"id":1687404259145,"name":"Dignus Est","year":"2029","country":"Croácia","destination":"Pluto"},{"id":1687404294325,"name":"Dignus Est","year":"2029","country":"Croácia","destination":"Pluto"}]